{
    "AX": {
        "error": 0.003462365512995321,
        "error_type": "SEM",
        "filter_outliers_dict": {
            "filter_outliers": true,
            "iterations": 1,
            "std_devs": 2
        },
        "fit": "Average",
        "value": -0.01783310993540182
    },
    "CDD": {
        "error": 1.294180043658111e-06,
        "error_type": "SEM",
        "filter_outliers_dict": {
            "filter_outliers": false,
            "iterations": 1,
            "std_devs": 2
        },
        "fit": "Average",
        "value": -2.0427541474604246e-06
    },
    "H1": {
        "error": 0.008742101574231243,
        "error_type": "SEM",
        "filter_outliers_dict": {
            "filter_outliers": true,
            "iterations": 1,
            "std_devs": 2
        },
        "fit": "Average",
        "value": -0.13161534331288488
    },
    "H2": {
        "error": 0.0088857680880121,
        "error_type": "SEM",
        "filter_outliers_dict": {
            "filter_outliers": true,
            "iterations": 1,
            "std_devs": 2
        },
        "fit": "Average",
        "value": -0.06871731385460925
    },
    "L1": {
        "error": 0.007267932866436936,
        "error_type": "SEM",
        "filter_outliers_dict": {
            "filter_outliers": true,
            "iterations": 1,
            "std_devs": 2
        },
        "fit": "Average",
        "value": -0.06156258482338349
    },
    "L2": {
        "error": 0.004048865484943329,
        "error_type": "SEM",
        "filter_outliers_dict": {
            "filter_outliers": false,
            "iterations": 1,
            "std_devs": 2
        },
        "fit": "Average",
        "value": -0.002972056532241364
    }
}